remove_slash/__init__.py
remove_slash/middleware.py
bear_django_remove_trailing_slash-0.1.0.dist-info/METADATA
bear_django_remove_trailing_slash-0.1.0.dist-info/WHEEL
bear_django_remove_trailing_slash-0.1.0.dist-info/top_level.txt
bear_django_remove_trailing_slash-0.1.0.dist-info/RECORD
