Metadata-Version: 2.4
Name: bear-django-remove-trailing-slash
Version: 0.1.0
Summary: A Django middleware that removes trailing slashes from URLs for SEO purposes.
Author-email: Bohdan Riabunets <bearablyk@gmail.com>
License-Expression: MIT
Project-URL: Homepage, https://github.com/bearablyk/django-remove-trailing-slash
Project-URL: Issues, https://github.com/bearablyk/django-remove-trailing-slash/issues
Classifier: Programming Language :: Python :: 3
Classifier: Operating System :: OS Independent
Classifier: Framework :: Django
Classifier: Topic :: Internet :: WWW/HTTP :: WSGI :: Middleware
Requires-Python: >=3.8
Requires-Dist: Django>=3.2
